st_video_player/__init__.py
st_video_player/frontend/build/asset-manifest.json
st_video_player/frontend/build/bootstrap.min.css
st_video_player/frontend/build/index.html
st_video_player/frontend/build/static/js/main.69609ade.js
st_video_player/frontend/build/static/js/main.69609ade.js.LICENSE.txt
st_video_player/frontend/build/static/js/main.69609ade.js.map
st_video_player-0.0.8.dist-info/METADATA
st_video_player-0.0.8.dist-info/WHEEL
st_video_player-0.0.8.dist-info/top_level.txt
st_video_player-0.0.8.dist-info/RECORD
