Metadata-Version: 2.1
Name: st-video-player
Version: 0.0.8
Summary: Streamlit component that allows you to play videos from bytes
Home-page: 
Author: William Reyes
Author-email: william.reyes@mlse.com
Requires-Python: >=3.7
Requires-Dist: streamlit >=0.63
Provides-Extra: devel
Requires-Dist: wheel ; extra == 'devel'
Requires-Dist: pytest ==7.4.0 ; extra == 'devel'
Requires-Dist: playwright ==1.36.0 ; extra == 'devel'
Requires-Dist: requests ==2.31.0 ; extra == 'devel'
Requires-Dist: pytest-playwright-snapshot ==1.0 ; extra == 'devel'
Requires-Dist: pytest-rerunfailures ==12.0 ; extra == 'devel'
